aws_fsx_lifecycle_status_monitor/__init__.py
aws_fsx_lifecycle_status_monitor/py.typed
aws_fsx_lifecycle_status_monitor/_jsii/__init__.py
aws_fsx_lifecycle_status_monitor/_jsii/aws-fsx-lifecycle-status-monitor@0.0.38.jsii.tgz
aws_fsx_lifecycle_status_monitor-0.0.38.dist-info/LICENSE
aws_fsx_lifecycle_status_monitor-0.0.38.dist-info/METADATA
aws_fsx_lifecycle_status_monitor-0.0.38.dist-info/WHEEL
aws_fsx_lifecycle_status_monitor-0.0.38.dist-info/top_level.txt
aws_fsx_lifecycle_status_monitor-0.0.38.dist-info/RECORD
